mcstasscript/__init__.py
mcstasscript/_version.py
mcstasscript/configuration.yaml
mcstasscript/data/MCPLDataFormat.py
mcstasscript/data/McStasDataFormat.py
mcstasscript/data/__init__.py
mcstasscript/data/data.py
mcstasscript/data/pyvinylData.py
mcstasscript/helper/__init__.py
mcstasscript/helper/beam_dump_database.py
mcstasscript/helper/check_mccode_version.py
mcstasscript/helper/component_reader.py
mcstasscript/helper/exceptions.py
mcstasscript/helper/formatting.py
mcstasscript/helper/managed_mcrun.py
mcstasscript/helper/mcstas_objects.py
mcstasscript/helper/name_inspector.py
mcstasscript/helper/plot_helper.py
mcstasscript/helper/search_statement.py
mcstasscript/helper/unpickler.py
mcstasscript/instr_reader/__init__.py
mcstasscript/instr_reader/control.py
mcstasscript/instr_reader/read_declare.py
mcstasscript/instr_reader/read_definition.py
mcstasscript/instr_reader/read_finally.py
mcstasscript/instr_reader/read_initialize.py
mcstasscript/instr_reader/read_trace.py
mcstasscript/instr_reader/read_uservars.py
mcstasscript/instr_reader/util.py
mcstasscript/instrument_diagnostics/__init__.py
mcstasscript/instrument_diagnostics/beam_diagnostics.py
mcstasscript/instrument_diagnostics/diagnostics_instrument.py
mcstasscript/instrument_diagnostics/event_plotter.py
mcstasscript/instrument_diagnostics/intensity_diagnostics.py
mcstasscript/instrument_diagnostics/plot_overview.py
mcstasscript/instrument_diagnostics/view.py
mcstasscript/instrument_diagram/__init__.py
mcstasscript/instrument_diagram/arrow.py
mcstasscript/instrument_diagram/box.py
mcstasscript/instrument_diagram/canvas.py
mcstasscript/instrument_diagram/component_description.py
mcstasscript/instrument_diagram/connections.py
mcstasscript/instrument_diagram/generate_AT.py
mcstasscript/instrument_diagram/generate_GROUP.py
mcstasscript/instrument_diagram/generate_JUMP.py
mcstasscript/instrument_diagram/generate_ROTATED.py
mcstasscript/instrument_diagram/generate_Union.py
mcstasscript-0.0.77.dist-info/licenses/LICENSE
mcstasscript-0.0.77.dist-info/METADATA
mcstasscript-0.0.77.dist-info/WHEEL
mcstasscript-0.0.77.dist-info/top_level.txt
mcstasscript-0.0.77.dist-info/RECORD
