Metadata-Version: 2.4
Name: McStasScript
Version: 0.0.77
Summary: A python scripting interface for McStas
Home-page: https://github.com/PaNOSC-ViNYL/McStasScript
Author: Mads Bertelsen
Author-email: Mads.Bertelsen@ess.eu
Classifier: Programming Language :: Python :: 3
Classifier: License :: OSI Approved :: GNU General Public License (GPL)
Classifier: Operating System :: OS Independent
Classifier: Topic :: Scientific/Engineering
License-File: LICENSE
Requires-Dist: numpy
Requires-Dist: matplotlib
Requires-Dist: PyYAML
Requires-Dist: ipywidgets
Requires-Dist: libpyvinyl
Dynamic: author
Dynamic: author-email
Dynamic: classifier
Dynamic: description
Dynamic: description-content-type
Dynamic: home-page
Dynamic: license-file
Dynamic: requires-dist
Dynamic: summary
